scriptprof/__init__.py
scriptprof/config.yaml
scriptprof/main.py
script_prof-0.0.2.dist-info/METADATA
script_prof-0.0.2.dist-info/WHEEL
script_prof-0.0.2.dist-info/entry_points.txt
script_prof-0.0.2.dist-info/top_level.txt
script_prof-0.0.2.dist-info/RECORD
